dastyletools/__init__.py
dastyletools/tools.py
dastyletools-0.0.4.dist-info/METADATA
dastyletools-0.0.4.dist-info/WHEEL
dastyletools-0.0.4.dist-info/top_level.txt
dastyletools-0.0.4.dist-info/RECORD
